pycran/__init__.py
pycran/errors.py
pycran/typings.py
pycran/util.py
pycran-0.2.0.dist-info/LICENSE
pycran-0.2.0.dist-info/WHEEL
pycran-0.2.0.dist-info/METADATA
pycran-0.2.0.dist-info/RECORD
