Metadata-Version: 2.1
Name: pycran
Version: 0.2.0
Summary: Parse CRAN package metadata
Home-page: https://github.com/imanhodjaev/pycran
License: UNKNOWN
Keywords: CRAN,R,metadata,parse,yamp
Author: Sultan Iman
Author-email: sultan.imanhodjaev@gmail.com
Requires-Python: >=3.6
Classifier: License :: OSI Approved :: Apache Software License
Classifier: Development Status :: 4 - Beta
Classifier: Programming Language :: Python :: 3 :: Only
Classifier: Programming Language :: Python :: 3.6
Classifier: Programming Language :: Python :: 3.7
Classifier: Programming Language :: Python :: 3.8
Classifier: Operating System :: OS Independent
Classifier: Intended Audience :: Developers
Classifier: Natural Language :: English
Classifier: Topic :: Software Development :: Libraries :: Python Modules
Classifier: Topic :: Software Development :: Libraries
Classifier: Topic :: Software Development
Classifier: Typing :: Typed
Requires-Dist: bumpversion ; extra == "dev"
Requires-Dist: deb-pkg-tools>=7.0 ; extra == "dev"
Requires-Dist: black==19.10b0 ; extra == "dev"
Requires-Dist: isort ; extra == "dev"
Requires-Dist: mypy ; extra == "dev"
Requires-Dist: pytest ; extra == "test"
Requires-Dist: pytest-cov ; extra == "test"
Provides-Extra: dev
Provides-Extra: test
